{
  "name": "Lucas Rattz",
  "description": "Kubernetes Enjoyer",
  "profilePicture": "static/assets/profile.webp",
  "favicon": "static/assets/favicon.ico",
  "render": false,
  "sections": [
    {
      "title": "About",
      "kind": 0,
      "entries": [
        {
          "entryDescription": "Hi, I'm Lucas, a DevOps/Platform engineer focused on building cloud native solutions. Trying to do something new every day. Probably self-hosting some shiny new service or writing a RPG campaign right now.",
          "url": "/codex"
        }
      ]
    },
    {
      "title": "Professional Experience",
      "kind": 1,
      "entries": [
        {
          "timeframe": "2023 – present",
          "entryName": "DevOps Engineer - Syself GmbH",
          "entryDescription": "Building a Kubernetes platform based on Cluster API for delivering production-ready clusters with a single click on Hetzner cloud and bare metal. Also doing Kubernetes consulting and writing technical content for articles and docs.",
          "url": "https://syself.com",
          "stack": [
            "Kubernetes",
            "Go",
            "Bash",
            "Hetzner"
          ]
        },
        {
          "timeframe": "2022 – 2023",
          "entryName": "DevOps Engineer - EZOps.cloud",
          "entryDescription": "Involved in the entire lifecycle of projects, implementing continuous integration and delivery, infrastructure as code, configuration management and monitoring solutions.",
          "url": "https://ezops.cloud",
          "stack": [
            "AWS",
            "Kubernetes",
            "Terraform",
            "Ansible"
          ]
        },
        {
          "timeframe": "2022 – 2022",
          "entryName": "Teaching Assistant - CEFET/RJ",
          "entryDescription": "Assisted first year students in C programming classes. Developed a widely adopted platform in the campus for students to share study materials.",
          "url": "https://www.cefet-rj.br",
          "stack": [
            "C"
          ]
        },
        {
          "timeframe": "2021 – 2021",
          "entryName": "Full Stack Developer - Reder Software",
          "entryDescription": "Provided levels 2 and 3 technical support for Magento 2 e-commerce stores, ERP and POS software. Developed custom modules and integrations.",
          "url": "https://redersoftware.com.br",
          "stack": [
            "Magento",
            "Google Cloud",
            "PHP",
            "Laravel"
          ]
        }
      ]
    },
    {
      "title": "Projects",
      "kind": 3,
      "entries": [
        {
          "timeframe": "ongoing",
          "projectIcon": "static/assets/cefetdb.svg",
          "entryName": "CEFETDB",
          "entryDescription": "A widely adopted platform for CEFET/RJ Information Systems alumni to share study materials. Currently working in a refactor.",
          "url": "https://cefetdb.rattz.xyz",
          "stack": [
            "Go",
            "JavaScript"
          ]
        },
        {
          "timeframe": "2023",
          "projectIcon": "static/assets/bladehub.svg",
          "entryName": "Bladehub",
          "entryDescription": "A fork of Tim Pasquini's Blades in the Dark Generators with a web front-end.",
          "url": "https://lucasrattz.github.io/bladehub/",
          "stack": [
            "Python",
            "JavaScript"
          ]
        }
      ]
    },
    {
      "title": "Links",
      "kind": 4,
      "entries": [
        {
          "timeframe": "GitHub",
          "entryName": "lucasrattz",
          "url": "https://github.com/lucasrattz",
          "relMe": true
        },
        {
          "timeframe": "LinkedIn",
          "entryName": "Lucas Rattz",
          "url": "https://linkedin.com/in/lucasrattz"
        },
        {
          "timeframe": "Resumé",
          "entryName": "Drive Link",
          "url": "https://drive.google.com/file/d/1ZI2VB5SMOxKgO2UF7inEDzv2B1wBVcQE/view?usp=drive_link"
        }
      ]
    }
  ]
}
